SubBrainSegment/__init__.py
SubBrainSegment/__main__.py
SubBrainSegment/segment.py
SubBrainSegment/unet3d/__init__.py
SubBrainSegment/unet3d/augment.py
SubBrainSegment/unet3d/data.py
SubBrainSegment/unet3d/datapredict.py
SubBrainSegment/unet3d/generator.py
SubBrainSegment/unet3d/metrics.py
SubBrainSegment/unet3d/normalize.py
SubBrainSegment/unet3d/prediction.py
SubBrainSegment/unet3d/training.py
SubBrainSegment/unet3d/model/__init__.py
SubBrainSegment/unet3d/model/isensee2017.py
SubBrainSegment/unet3d/model/unet.py
SubBrainSegment/unet3d/utils/__init__.py
SubBrainSegment/unet3d/utils/patches.py
SubBrainSegment/unet3d/utils/sitk_utils.py
SubBrainSegment/unet3d/utils/utils.py
SubBrainSegment/unet3d/utils/nilearn_custom_utils/__init__.py
SubBrainSegment/unet3d/utils/nilearn_custom_utils/nilearn_utils.py
SubBrainSegment-0.1.0.dist-info/LICENCE.txt
SubBrainSegment-0.1.0.dist-info/METADATA
SubBrainSegment-0.1.0.dist-info/WHEEL
SubBrainSegment-0.1.0.dist-info/top_level.txt
SubBrainSegment-0.1.0.dist-info/RECORD
